ldm/__init__.py
ldm/__main__.py
ldm/api/__init__.py
ldm/api/config/__init__.py
ldm/api/config/_dependency.py
ldm/api/config/_installer.py
ldm/api/config/_scheme.py
ldm/api/factory/__init__.py
ldm/api/factory/_factory.py
ldm/api/factory/_github.py
ldm/api/factory/_http.py
ldm/api/factory/_https.py
ldm/api/installer/__init__.py
ldm/api/installer/_dependency.py
ldm/api/installer/_installer.py
ldm/api/installer/strategy/__init__.py
ldm/api/installer/strategy/_create.py
ldm/api/installer/strategy/_parallel.py
ldm/api/installer/strategy/_sequential.py
ldm/api/installer/strategy/_strategy.py
ldm/api/parse.py
ldm/api/scheme/__init__.py
ldm/api/scheme/_github.py
ldm/api/scheme/_http.py
ldm/api/scheme/_scheme.py
ldm/cli/__init__.py
ldm/cli/_cli.py
ldm/cli/_error.py
ldm/cli/_logger.py
ldm/commands/__init__.py
ldm/commands/_command.py
ldm/commands/_install.py
ldm/component.py
ldm/logger/__init__.py
ldm/logger/_click_logger.py
ldm/logger/_logger.py
ldm/logger/_noop_logger.py
ldm/utils/__init__.py
ldm/utils/mapping/__init__.py
ldm/utils/mapping/_subscriptable.py
loose_dependency_manager-0.4.0.dist-info/LICENSE
loose_dependency_manager-0.4.0.dist-info/METADATA
loose_dependency_manager-0.4.0.dist-info/WHEEL
loose_dependency_manager-0.4.0.dist-info/entry_points.txt
loose_dependency_manager-0.4.0.dist-info/RECORD
