Metadata-Version: 2.1
Name: loose-dependency-manager
Version: 0.4.0
Summary: Tool for managing code dependencies in a loosely-coupled way.
License: MIT
Author: 01Joseph-Hwang10
Author-email: joseph95501@gmail.com
Requires-Python: >=3.8.1,<4.0
Classifier: Development Status :: 5 - Production/Stable
Classifier: Intended Audience :: Developers
Classifier: License :: OSI Approved :: MIT License
Classifier: Natural Language :: English
Classifier: Programming Language :: Python :: 3
Classifier: Programming Language :: Python :: 3.9
Classifier: Programming Language :: Python :: 3.10
Classifier: Programming Language :: Python :: 3.11
Classifier: Programming Language :: Python :: 3.12
Classifier: Programming Language :: Python :: 3 :: Only
Classifier: Programming Language :: Python :: 3.13
Classifier: Programming Language :: Python :: 3.8
Classifier: Programming Language :: Python :: Implementation :: CPython
Classifier: Programming Language :: Python :: Implementation :: PyPy
Classifier: Topic :: Software Development
Classifier: Topic :: Software Development :: Libraries :: Python Modules
Classifier: Topic :: Utilities
Requires-Dist: click (>=8.1.7,<9.0.0)
Requires-Dist: colorama (>=0.4.6,<0.5.0)
Requires-Dist: git-remote-get (>=0.3.1,<0.4.0)
Requires-Dist: httpx (>=0.27.0,<0.28.0)
Requires-Dist: pydantic (>=2.7.1,<3.0.0)
Requires-Dist: yaml-replace (>=1.1.2,<2.0.0)
